o2wb/__init.py__
o2wb/exp.py
o2wb/imp.py
o2wb-0.1.11.dist-info/entry_points.txt
o2wb-0.1.11.dist-info/WHEEL
o2wb-0.1.11.dist-info/METADATA
o2wb-0.1.11.dist-info/RECORD
