Metadata-Version: 2.1
Name: o2wb
Version: 0.1.11
Summary: 
License: MIT
Author: DPKM
Requires-Python: >=3.10
Classifier: License :: OSI Approved :: MIT License
Classifier: Programming Language :: Python :: 3
Classifier: Programming Language :: Python :: 3.10
Classifier: Programming Language :: Python :: 3.11
Requires-Dist: argparse (>=1.4.0,<1.5.0)
Requires-Dist: html5lib (>=1.1.0,<1.2.0)
Requires-Dist: rdflib (>=6.2.0,<6.3.0)
Requires-Dist: wikibaseintegrator (>=0.12.2,<0.13.0)
